[{"place_id": 353592, "licence": "Data \u00a9 OpenStreetMap contributors, ODbL 1.0. https://osm.org/copyright", "osm_type": "node", "osm_id": 150968654, "boundingbox": ["38.3687993", "38.4487993", "-121.4116178", "-121.3316178"], "lat": "38.4087993", "lon": "-121.3716178", "display_name": "Elk Grove, Sacramento County, California, 94624, United States", "class": "place", "type": "town", "importance": 0.7570487834620994, "icon": "https://nominatim.openstreetmap.org/ui/mapicons//poi_place_town.p.20.png", "geojson": {"type": "Point", "coordinates": [-121.3716178, 38.4087993]}}, {"place_id": 88075727, "licence": "Data \u00a9 OpenStreetMap contributors, ODbL 1.0. https://osm.org/copyright", "osm_type": "way", "osm_id": 13358364, "boundingbox": ["33.6676924", "33.6686695", "-117.7817486", "-117.7812056"], "lat": "33.6682144", "lon": "-117.781435", "display_name": "Elk Grove, Oak Creek, Irvine, Orange County, California, 92618, United States", "class": "highway", "type": "residential", "importance": 0.41000000000000003, "geojson": {"type": "LineString", "coordinates": [[-117.7817486, 33.6676924], [-117.781435, 33.6682144], [-117.781254, 33.6685811], [-117.7812056, 33.6686695]]}}]