[{"place_id": 327202, "licence": "Data \u00a9 OpenStreetMap contributors, ODbL 1.0. https://osm.org/copyright", "osm_type": "node", "osm_id": 150932798, "boundingbox": ["36.6724476", "36.7124476", "-119.0723321", "-119.0323321"], "lat": "36.6924476", "lon": "-119.0523321", "display_name": "Miramonte, Fresno County, California, 93641, United States", "class": "place", "type": "hamlet", "importance": 0.6143607584280288, "icon": "https://nominatim.openstreetmap.org/ui/mapicons//poi_place_village.p.20.png", "geojson": {"type": "Point", "coordinates": [-119.0523321, 36.6924476]}}, {"place_id": 85442197, "licence": "Data \u00a9 OpenStreetMap contributors, ODbL 1.0. https://osm.org/copyright", "osm_type": "way", "osm_id": 5964243, "boundingbox": ["32.722511", "32.724991", "-116.859558", "-116.858833"], "lat": "32.723984", "lon": "-116.859123", "display_name": "Miramonte, San Diego County, California, 91935, United States", "class": "highway", "type": "residential", "importance": 0.32, "geojson": {"type": "LineString", "coordinates": [[-116.858833, 32.722511], [-116.858871, 32.723087], [-116.858902, 32.72332], [-116.859123, 32.723984], [-116.859242, 32.724307], [-116.859451, 32.724876], [-116.859558, 32.724991]]}}]